pygryfsmart/__init__.py
pygryfsmart/const.py
pygryfsmart/cover.py
pygryfsmart/api/__init__.py
pygryfsmart/api/api.py
pygryfsmart/api/communications.py
pygryfsmart/api/const.py
pygryfsmart/api/feedback.py
pygryfsmart/api/functions.py
pygryfsmart/api/gryf_expert.py
pygryfsmart/api/parsing.py
pygryfsmart/api/rs232.py
pygryfsmart/api/tcp.py
pygryfsmart/api/typing.py
pygryfsmart/device/__init__.py
pygryfsmart/device/base.py
pygryfsmart/device/classic_cover.py
pygryfsmart/device/expert.py
pygryfsmart/device/input.py
pygryfsmart/device/input_line.py
pygryfsmart/device/lock.py
pygryfsmart/device/output.py
pygryfsmart/device/output_line.py
pygryfsmart/device/pcover.py
pygryfsmart/device/pwm.py
pygryfsmart/device/reset.py
pygryfsmart/device/temperature.py
pygryfsmart/device/thermostat.py
pygryfsmart-0.3.4.dist-info/licenses/LICENSE
tests/__init__.py
tests/test_api_communciation.py
tests/test_feedback.py
tests/test_rs232.py
pygryfsmart-0.3.4.dist-info/METADATA
pygryfsmart-0.3.4.dist-info/WHEEL
pygryfsmart-0.3.4.dist-info/top_level.txt
pygryfsmart-0.3.4.dist-info/RECORD
