Metadata-Version: 2.4
Name: pygryfsmart
Version: 0.3.4
Summary: Library for the GryfSmart system
Home-page: https://github.com/karlowiczpl/pygryfsmart
Author: @karlowiczpl
Author-email: k.karlowski@outlook.com
License: MIT
Classifier: Programming Language :: Python :: 3
Classifier: Operating System :: OS Independent
Requires-Python: >=3.8
License-File: LICENSE
Requires-Dist: pyserial-asyncio==0.6
Dynamic: license-file
